{
  "annotations": {
    "list": [
      {
        "builtIn": 1,
        "datasource": "-- Grafana --",
        "enable": true,
        "hide": true,
        "iconColor": "rgba(0, 211, 255, 1)",
        "name": "Annotations & Alerts",
        "type": "dashboard"
      }
    ]
  },
  "editable": true,
  "fiscalYearStartMonth": 0,
  "graphTooltip": 0,
  "id": null,
  "links": [],
  "liveNow": true,
  "panels": [
    {
      "type": "row",
      "title": "🏥 调度器健康",
      "collapsed": false,
      "gridPos": {
        "h": 1,
        "w": 24,
        "x": 0,
        "y": 0
      },
      "id": 45668
    },
    {
      "type": "stat",
      "title": "调度器运行状态",
      "id": 52351,
      "gridPos": {
        "h": 4,
        "w": 4,
        "x": 0,
        "y": 1
      },
      "datasource": {
        "type": "prometheus",
        "uid": "prometheus"
      },
      "targets": [
        {
          "expr": "stock_scheduler_running",
          "refId": "A"
        }
      ],
      "fieldConfig": {
        "defaults": {
          "thresholds": {
            "mode": "absolute",
            "steps": [
              {
                "color": "green",
                "value": null
              }
            ]
          },
          "unit": "short",
          "mappings": [
            {
              "options": {
                "0": {
                  "text": "停止",
                  "color": "red"
                }
              },
              "type": "value"
            },
            {
              "options": {
                "1": {
                  "text": "运行中",
                  "color": "green"
                }
              },
              "type": "value"
            }
          ]
        }
      },
      "options": {
        "reduceOptions": {
          "calcs": [
            "lastNotNull"
          ]
        },
        "colorMode": "value",
        "graphMode": "area",
        "textMode": "auto"
      }
    },
    {
      "type": "stat",
      "title": "24h Job 运行",
      "id": 95142,
      "gridPos": {
        "h": 4,
        "w": 4,
        "x": 4,
        "y": 1
      },
      "datasource": {
        "type": "prometheus",
        "uid": "prometheus"
      },
      "targets": [
        {
          "expr": "sum(stock:job_success_rate_1h) or vector(0)",
          "refId": "A"
        }
      ],
      "fieldConfig": {
        "defaults": {
          "thresholds": {
            "mode": "absolute",
            "steps": [
              {
                "color": "blue",
                "value": null
              }
            ]
          },
          "unit": "short"
        }
      },
      "options": {
        "reduceOptions": {
          "calcs": [
            "lastNotNull"
          ]
        },
        "colorMode": "value",
        "graphMode": "area",
        "textMode": "auto"
      }
    },
    {
      "type": "stat",
      "title": "24h 任务数",
      "id": 42496,
      "gridPos": {
        "h": 4,
        "w": 4,
        "x": 8,
        "y": 1
      },
      "datasource": {
        "type": "prometheus",
        "uid": "prometheus"
      },
      "targets": [
        {
          "expr": "sum(increase(stock_job_runs_total[24h]))",
          "refId": "A"
        }
      ],
      "fieldConfig": {
        "defaults": {
          "thresholds": {
            "mode": "absolute",
            "steps": [
              {
                "color": "purple",
                "value": null
              }
            ]
          },
          "unit": "short"
        }
      },
      "options": {
        "reduceOptions": {
          "calcs": [
            "lastNotNull"
          ]
        },
        "colorMode": "value",
        "graphMode": "area",
        "textMode": "auto"
      }
    },
    {
      "type": "stat",
      "title": "API 流量 (req/h)",
      "id": 90618,
      "gridPos": {
        "h": 4,
        "w": 4,
        "x": 12,
        "y": 1
      },
      "datasource": {
        "type": "prometheus",
        "uid": "prometheus"
      },
      "targets": [
        {
          "expr": "sum(increase(stock_api_requests_total[1h]))",
          "refId": "A"
        }
      ],
      "fieldConfig": {
        "defaults": {
          "thresholds": {
            "mode": "absolute",
            "steps": [
              {
                "color": "orange",
                "value": null
              }
            ]
          },
          "unit": "short"
        }
      },
      "options": {
        "reduceOptions": {
          "calcs": [
            "lastNotNull"
          ]
        },
        "colorMode": "value",
        "graphMode": "area",
        "textMode": "auto"
      }
    },
    {
      "type": "stat",
      "title": "飞书推送 (1h)",
      "id": 51548,
      "gridPos": {
        "h": 4,
        "w": 4,
        "x": 16,
        "y": 1
      },
      "datasource": {
        "type": "prometheus",
        "uid": "prometheus"
      },
      "targets": [
        {
          "expr": "sum(increase(stock_feishu_pushes_total[1h]))",
          "refId": "A"
        }
      ],
      "fieldConfig": {
        "defaults": {
          "thresholds": {
            "mode": "absolute",
            "steps": [
              {
                "color": "cyan",
                "value": null
              }
            ]
          },
          "unit": "short"
        }
      },
      "options": {
        "reduceOptions": {
          "calcs": [
            "lastNotNull"
          ]
        },
        "colorMode": "value",
        "graphMode": "area",
        "textMode": "auto"
      }
    },
    {
      "type": "stat",
      "title": "DB 大小 (MB)",
      "id": 27696,
      "gridPos": {
        "h": 4,
        "w": 4,
        "x": 20,
        "y": 1
      },
      "datasource": {
        "type": "prometheus",
        "uid": "prometheus"
      },
      "targets": [
        {
          "expr": "stock:db_size_mb",
          "refId": "A"
        }
      ],
      "fieldConfig": {
        "defaults": {
          "thresholds": {
            "mode": "absolute",
            "steps": [
              {
                "color": "blue",
                "value": null
              }
            ]
          },
          "unit": "decmbytes"
        }
      },
      "options": {
        "reduceOptions": {
          "calcs": [
            "lastNotNull"
          ]
        },
        "colorMode": "value",
        "graphMode": "area",
        "textMode": "auto"
      }
    },
    {
      "type": "row",
      "title": "📈 任务执行速率",
      "collapsed": false,
      "gridPos": {
        "h": 1,
        "w": 24,
        "x": 0,
        "y": 5
      },
      "id": 63463
    },
    {
      "type": "timeseries",
      "title": "各任务执行速率 (按状态)",
      "id": 57993,
      "gridPos": {
        "h": 8,
        "w": 12,
        "x": 0,
        "y": 6
      },
      "datasource": {
        "type": "prometheus",
        "uid": "prometheus"
      },
      "targets": [
        {
          "expr": "sum by (job_id, status) (rate(stock_job_runs_total[5m]))",
          "legendFormat": "{{job_id}} - {{status}}",
          "refId": "A"
        }
      ],
      "fieldConfig": {
        "defaults": {
          "custom": {
            "drawStyle": "line",
            "lineWidth": 2,
            "fillOpacity": 20
          },
          "unit": "ops"
        }
      },
      "options": {
        "legend": {
          "displayMode": "list",
          "placement": "bottom"
        },
        "tooltip": {
          "mode": "multi"
        }
      }
    },
    {
      "type": "timeseries",
      "title": "任务成功率 (1h rolling)",
      "id": 89117,
      "gridPos": {
        "h": 8,
        "w": 12,
        "x": 12,
        "y": 6
      },
      "datasource": {
        "type": "prometheus",
        "uid": "prometheus"
      },
      "targets": [
        {
          "expr": "stock:job_success_rate_1h",
          "legendFormat": "{{job_id}}",
          "refId": "A"
        }
      ],
      "fieldConfig": {
        "defaults": {
          "custom": {
            "drawStyle": "line",
            "lineWidth": 2,
            "fillOpacity": 20
          },
          "unit": "percentunit"
        }
      },
      "options": {
        "legend": {
          "displayMode": "list",
          "placement": "bottom"
        },
        "tooltip": {
          "mode": "multi"
        }
      }
    },
    {
      "type": "row",
      "title": "🛜 API 性能",
      "collapsed": false,
      "gridPos": {
        "h": 1,
        "w": 24,
        "x": 0,
        "y": 14
      },
      "id": 97902
    },
    {
      "type": "timeseries",
      "title": "API 请求数/秒 (按状态码)",
      "id": 1714,
      "gridPos": {
        "h": 8,
        "w": 12,
        "x": 0,
        "y": 15
      },
      "datasource": {
        "type": "prometheus",
        "uid": "prometheus"
      },
      "targets": [
        {
          "expr": "sum by (status) (rate(stock_api_requests_total[5m]))",
          "legendFormat": "{{status}}",
          "refId": "A"
        }
      ],
      "fieldConfig": {
        "defaults": {
          "custom": {
            "drawStyle": "line",
            "lineWidth": 2,
            "fillOpacity": 20
          },
          "unit": "reqps"
        }
      },
      "options": {
        "legend": {
          "displayMode": "list",
          "placement": "bottom"
        },
        "tooltip": {
          "mode": "multi"
        }
      }
    },
    {
      "type": "timeseries",
      "title": "API 延迟 p50/p95/p99",
      "id": 17700,
      "gridPos": {
        "h": 8,
        "w": 12,
        "x": 12,
        "y": 15
      },
      "datasource": {
        "type": "prometheus",
        "uid": "prometheus"
      },
      "targets": [
        {
          "expr": "histogram_quantile(0.5, sum(rate(stock_api_request_duration_seconds_bucket[5m])) by (le))",
          "legendFormat": "p50",
          "refId": "A"
        }
      ],
      "fieldConfig": {
        "defaults": {
          "custom": {
            "drawStyle": "line",
            "lineWidth": 2,
            "fillOpacity": 20
          },
          "unit": "s"
        }
      },
      "options": {
        "legend": {
          "displayMode": "list",
          "placement": "bottom"
        },
        "tooltip": {
          "mode": "multi"
        }
      }
    },
    {
      "type": "row",
      "title": "💾 资源使用",
      "collapsed": false,
      "gridPos": {
        "h": 1,
        "w": 24,
        "x": 0,
        "y": 23
      },
      "id": 36409
    },
    {
      "type": "timeseries",
      "title": "DB 大小增长 (24h)",
      "id": 39306,
      "gridPos": {
        "h": 8,
        "w": 8,
        "x": 0,
        "y": 24
      },
      "datasource": {
        "type": "prometheus",
        "uid": "prometheus"
      },
      "targets": [
        {
          "expr": "stock:db_size_mb",
          "legendFormat": "",
          "refId": "A"
        }
      ],
      "fieldConfig": {
        "defaults": {
          "custom": {
            "drawStyle": "line",
            "lineWidth": 2,
            "fillOpacity": 20
          },
          "unit": "decmbytes"
        }
      },
      "options": {
        "legend": {
          "displayMode": "list",
          "placement": "bottom"
        },
        "tooltip": {
          "mode": "multi"
        }
      }
    },
    {
      "type": "timeseries",
      "title": "事件数趋势 (24h)",
      "id": 25391,
      "gridPos": {
        "h": 8,
        "w": 8,
        "x": 8,
        "y": 24
      },
      "datasource": {
        "type": "prometheus",
        "uid": "prometheus"
      },
      "targets": [
        {
          "expr": "stock:events_growth_24h",
          "legendFormat": "",
          "refId": "A"
        }
      ],
      "fieldConfig": {
        "defaults": {
          "custom": {
            "drawStyle": "line",
            "lineWidth": 2,
            "fillOpacity": 20
          },
          "unit": "short"
        }
      },
      "options": {
        "legend": {
          "displayMode": "list",
          "placement": "bottom"
        },
        "tooltip": {
          "mode": "multi"
        }
      }
    },
    {
      "type": "timeseries",
      "title": "新闻抓取速率 (24h)",
      "id": 5567,
      "gridPos": {
        "h": 8,
        "w": 8,
        "x": 16,
        "y": 24
      },
      "datasource": {
        "type": "prometheus",
        "uid": "prometheus"
      },
      "targets": [
        {
          "expr": "stock:news_growth_24h",
          "legendFormat": "",
          "refId": "A"
        }
      ],
      "fieldConfig": {
        "defaults": {
          "custom": {
            "drawStyle": "line",
            "lineWidth": 2,
            "fillOpacity": 20
          },
          "unit": "short"
        }
      },
      "options": {
        "legend": {
          "displayMode": "list",
          "placement": "bottom"
        },
        "tooltip": {
          "mode": "multi"
        }
      }
    }
  ],
  "refresh": "30s",
  "schemaVersion": 38,
  "style": "dark",
  "tags": [
    "stock",
    "health",
    "ops"
  ],
  "templating": {
    "list": [
      {
        "current": {
          "selected": true,
          "text": "Prometheus",
          "value": "Prometheus"
        },
        "hide": 0,
        "includeAll": false,
        "label": "Datasource",
        "multi": false,
        "name": "datasource",
        "options": [],
        "query": "prometheus",
        "queryValue": "",
        "refresh": 1,
        "regex": "",
        "skipUrlSync": false,
        "type": "datasource"
      }
    ]
  },
  "time": {
    "from": "now-24h",
    "to": "now"
  },
  "timepicker": {},
  "timezone": "browser",
  "title": "System Health",
  "uid": "stock-system-health",
  "version": 1,
  "weekStart": ""
}